Metadata-Version: 1.1
Name: cs107-autodiff
Version: 0.2
Summary: Automated Differentiation based on forward and reverse mode
Home-page: UNKNOWN
Author: ShangShang Wang, Max Urbany, Meghna Banerjee, Mingcheng(Jason) Liu
Author-email: UNKNOWN
License: MIT
Keywords: FORWARD MODE,BACKWARD MODE,DERIVATIVES
Platform: UNKNOWN
Classifier: Development Status :: 3 - Alpha
Classifier: Intended Audience :: Developers
Classifier: Topic :: Software Development :: Build Tools
Classifier: License :: OSI Approved :: MIT License
Classifier: Programming Language :: Python :: 3.8
